delfick_project/__init__.py
delfick_project/addons.py
delfick_project/app.py
delfick_project/errors.py
delfick_project/errors_pytest.py
delfick_project/layerz.py
delfick_project/logging.py
delfick_project/version.py
delfick_project/norms/__init__.py
delfick_project/norms/errors.py
delfick_project/norms/field_spec.py
delfick_project/norms/meta.py
delfick_project/norms/obj.py
delfick_project/norms/spec_base.py
delfick_project/norms/validators.py
delfick_project/norms/sphinx/__init__.py
delfick_project/norms/sphinx/show_specs.py
delfick_project/option_merge/__init__.py
delfick_project/option_merge/collector.py
delfick_project/option_merge/converter.py
delfick_project/option_merge/formatter.py
delfick_project/option_merge/helper.py
delfick_project/option_merge/joiner.py
delfick_project/option_merge/merge.py
delfick_project/option_merge/not_found.py
delfick_project/option_merge/path.py
delfick_project/option_merge/storage.py
delfick_project/option_merge/value_at.py
delfick_project/option_merge/versioning.py
delfick_project-0.8.0.dist-info/METADATA
delfick_project-0.8.0.dist-info/WHEEL
delfick_project-0.8.0.dist-info/licenses/LICENSE
delfick_project-0.8.0.dist-info/RECORD
